<BinaryTree boostWeight="1.0e+00" itree="391" type="DecisionTree">
  <Variables NVar="20" />
  <Node Cut="17" IVar="10" NCoef="0" cType="1" depth="0" nType="0" pos="s" purity="0.0e+00" res="0.0e+00" rms="0.0e+00">
    <Node Cut="0.5" IVar="0" NCoef="0" cType="1" depth="1" nType="0" pos="l" purity="0.0e+00" res="0.0e+00" rms="0.0e+00">
      <Node Cut="9.5" IVar="19" NCoef="0" cType="1" depth="2" nType="0" pos="l" purity="0.0e+00" res="0.0e+00" rms="0.0e+00">
        <Node Cut="0.0e+00" IVar="-1" NCoef="0" cType="1" depth="3" nType="-99" pos="l" purity="0.0e+00" res="-0.00211999" rms="0.0e+00" />
        <Node Cut="0.0e+00" IVar="-1" NCoef="0" cType="1" depth="3" nType="-99" pos="r" purity="0.0e+00" res="0.00392034" rms="0.0e+00" />
      </Node>
      <Node Cut="3.5" IVar="11" NCoef="0" cType="1" depth="2" nType="0" pos="r" purity="0.0e+00" res="0.0e+00" rms="0.0e+00">
        <Node Cut="0.0e+00" IVar="-1" NCoef="0" cType="1" depth="3" nType="-99" pos="l" purity="0.0e+00" res="0.00146028" rms="0.0e+00" />
        <Node Cut="0.0e+00" IVar="-1" NCoef="0" cType="1" depth="3" nType="-99" pos="r" purity="0.0e+00" res="-0.00577238" rms="0.0e+00" />
      </Node>
    </Node>
    <Node Cut="26.5" IVar="10" NCoef="0" cType="1" depth="1" nType="0" pos="r" purity="0.0e+00" res="0.0e+00" rms="0.0e+00">
      <Node Cut="0.0e+00" IVar="-1" NCoef="0" cType="1" depth="2" nType="-99" pos="l" purity="0.0e+00" res="0.0022264" rms="0.0e+00" />
      <Node Cut="28.5" IVar="10" NCoef="0" cType="1" depth="2" nType="0" pos="r" purity="0.0e+00" res="0.0e+00" rms="0.0e+00">
        <Node Cut="0.0e+00" IVar="-1" NCoef="0" cType="1" depth="3" nType="-99" pos="l" purity="0.0e+00" res="-0.0023335" rms="0.0e+00" />
        <Node Cut="31.5" IVar="10" NCoef="0" cType="1" depth="3" nType="0" pos="r" purity="0.0e+00" res="0.0e+00" rms="0.0e+00">
          <Node Cut="0.0e+00" IVar="-1" NCoef="0" cType="1" depth="4" nType="-99" pos="l" purity="0.0e+00" res="0.00265007" rms="0.0e+00" />
          <Node Cut="34.5" IVar="10" NCoef="0" cType="1" depth="4" nType="0" pos="r" purity="0.0e+00" res="0.0e+00" rms="0.0e+00">
            <Node Cut="0.0e+00" IVar="-1" NCoef="0" cType="1" depth="5" nType="-99" pos="l" purity="0.0e+00" res="-0.00219957" rms="0.0e+00" />
            <Node Cut="0.0e+00" IVar="-1" NCoef="0" cType="1" depth="5" nType="-99" pos="r" purity="0.0e+00" res="5.62259e-05" rms="0.0e+00" />
          </Node>
        </Node>
      </Node>
    </Node>
  </Node>
</BinaryTree>
