<BinaryTree boostWeight="1.0e+00" itree="298" type="DecisionTree">
  <Variables NVar="10" />
  <Node Cut="18.5" IVar="9" NCoef="0" cType="1" depth="0" nType="0" pos="s" purity="0.0e+00" res="0.0e+00" rms="0.0e+00">
    <Node Cut="97" IVar="6" NCoef="0" cType="1" depth="1" nType="0" pos="l" purity="0.0e+00" res="0.0e+00" rms="0.0e+00">
      <Node Cut="95" IVar="6" NCoef="0" cType="1" depth="2" nType="0" pos="l" purity="0.0e+00" res="0.0e+00" rms="0.0e+00">
        <Node Cut="6.5" IVar="9" NCoef="0" cType="1" depth="3" nType="0" pos="l" purity="0.0e+00" res="0.0e+00" rms="0.0e+00">
          <Node Cut="93" IVar="6" NCoef="0" cType="1" depth="4" nType="0" pos="l" purity="0.0e+00" res="0.0e+00" rms="0.0e+00">
            <Node Cut="0.0e+00" IVar="-1" NCoef="0" cType="1" depth="5" nType="-99" pos="l" purity="0.0e+00" res="-4.50166e-05" rms="0.0e+00" />
            <Node Cut="0.0e+00" IVar="-1" NCoef="0" cType="1" depth="5" nType="-99" pos="r" purity="0.0e+00" res="-0.00615175" rms="0.0e+00" />
          </Node>
          <Node Cut="3.5" IVar="6" NCoef="0" cType="1" depth="4" nType="0" pos="r" purity="0.0e+00" res="0.0e+00" rms="0.0e+00">
            <Node Cut="0.0e+00" IVar="-1" NCoef="0" cType="1" depth="5" nType="-99" pos="l" purity="0.0e+00" res="-0.00782216" rms="0.0e+00" />
            <Node Cut="0.0e+00" IVar="-1" NCoef="0" cType="1" depth="5" nType="-99" pos="r" purity="0.0e+00" res="0.00229713" rms="0.0e+00" />
          </Node>
        </Node>
        <Node Cut="4.5" IVar="9" NCoef="0" cType="1" depth="3" nType="0" pos="r" purity="0.0e+00" res="0.0e+00" rms="0.0e+00">
          <Node Cut="0.0e+00" IVar="-1" NCoef="0" cType="1" depth="4" nType="-99" pos="l" purity="0.0e+00" res="0.0468244" rms="0.0e+00" />
          <Node Cut="6" IVar="4" NCoef="0" cType="1" depth="4" nType="0" pos="r" purity="0.0e+00" res="0.0e+00" rms="0.0e+00">
            <Node Cut="0.0e+00" IVar="-1" NCoef="0" cType="1" depth="5" nType="-99" pos="l" purity="0.0e+00" res="0.0062708" rms="0.0e+00" />
            <Node Cut="0.0e+00" IVar="-1" NCoef="0" cType="1" depth="5" nType="-99" pos="r" purity="0.0e+00" res="-0.00649133" rms="0.0e+00" />
          </Node>
        </Node>
      </Node>
      <Node Cut="1.5" IVar="4" NCoef="0" cType="1" depth="2" nType="0" pos="r" purity="0.0e+00" res="0.0e+00" rms="0.0e+00">
        <Node Cut="5.5" IVar="5" NCoef="0" cType="1" depth="3" nType="0" pos="l" purity="0.0e+00" res="0.0e+00" rms="0.0e+00">
          <Node Cut="0.5" IVar="7" NCoef="0" cType="1" depth="4" nType="0" pos="l" purity="0.0e+00" res="0.0e+00" rms="0.0e+00">
            <Node Cut="0.0e+00" IVar="-1" NCoef="0" cType="1" depth="5" nType="-99" pos="l" purity="0.0e+00" res="-0.00708991" rms="0.0e+00" />
            <Node Cut="0.0e+00" IVar="-1" NCoef="0" cType="1" depth="5" nType="-99" pos="r" purity="0.0e+00" res="0.0219346" rms="0.0e+00" />
          </Node>
          <Node Cut="3.5" IVar="9" NCoef="0" cType="1" depth="4" nType="0" pos="r" purity="0.0e+00" res="0.0e+00" rms="0.0e+00">
            <Node Cut="0.0e+00" IVar="-1" NCoef="0" cType="1" depth="5" nType="-99" pos="l" purity="0.0e+00" res="-0.00679462" rms="0.0e+00" />
            <Node Cut="0.0e+00" IVar="-1" NCoef="0" cType="1" depth="5" nType="-99" pos="r" purity="0.0e+00" res="-0.000135467" rms="0.0e+00" />
          </Node>
        </Node>
        <Node Cut="116.5" IVar="6" NCoef="0" cType="1" depth="3" nType="0" pos="r" purity="0.0e+00" res="0.0e+00" rms="0.0e+00">
          <Node Cut="2.5" IVar="5" NCoef="0" cType="1" depth="4" nType="0" pos="l" purity="0.0e+00" res="0.0e+00" rms="0.0e+00">
            <Node Cut="0.0e+00" IVar="-1" NCoef="0" cType="1" depth="5" nType="-99" pos="l" purity="0.0e+00" res="0.00280167" rms="0.0e+00" />
            <Node Cut="0.0e+00" IVar="-1" NCoef="0" cType="1" depth="5" nType="-99" pos="r" purity="0.0e+00" res="-0.00284818" rms="0.0e+00" />
          </Node>
          <Node Cut="17.5" IVar="9" NCoef="0" cType="1" depth="4" nType="0" pos="r" purity="0.0e+00" res="0.0e+00" rms="0.0e+00">
            <Node Cut="0.0e+00" IVar="-1" NCoef="0" cType="1" depth="5" nType="-99" pos="l" purity="0.0e+00" res="-3.00153e-05" rms="0.0e+00" />
            <Node Cut="0.0e+00" IVar="-1" NCoef="0" cType="1" depth="5" nType="-99" pos="r" purity="0.0e+00" res="0.00768275" rms="0.0e+00" />
          </Node>
        </Node>
      </Node>
    </Node>
    <Node Cut="0.5" IVar="2" NCoef="0" cType="1" depth="1" nType="0" pos="r" purity="0.0e+00" res="0.0e+00" rms="0.0e+00">
      <Node Cut="4.5" IVar="5" NCoef="0" cType="1" depth="2" nType="0" pos="l" purity="0.0e+00" res="0.0e+00" rms="0.0e+00">
        <Node Cut="103.5" IVar="6" NCoef="0" cType="1" depth="3" nType="0" pos="l" purity="0.0e+00" res="0.0e+00" rms="0.0e+00">
          <Node Cut="3.5" IVar="4" NCoef="0" cType="1" depth="4" nType="0" pos="l" purity="0.0e+00" res="0.0e+00" rms="0.0e+00">
            <Node Cut="0.0e+00" IVar="-1" NCoef="0" cType="1" depth="5" nType="-99" pos="l" purity="0.0e+00" res="-0.0141091" rms="0.0e+00" />
            <Node Cut="0.0e+00" IVar="-1" NCoef="0" cType="1" depth="5" nType="-99" pos="r" purity="0.0e+00" res="-0.00120927" rms="0.0e+00" />
          </Node>
          <Node Cut="4" IVar="4" NCoef="0" cType="1" depth="4" nType="0" pos="r" purity="0.0e+00" res="0.0e+00" rms="0.0e+00">
            <Node Cut="0.0e+00" IVar="-1" NCoef="0" cType="1" depth="5" nType="-99" pos="l" purity="0.0e+00" res="0.0198309" rms="0.0e+00" />
            <Node Cut="0.0e+00" IVar="-1" NCoef="0" cType="1" depth="5" nType="-99" pos="r" purity="0.0e+00" res="0.00215145" rms="0.0e+00" />
          </Node>
        </Node>
        <Node Cut="2.5" IVar="7" NCoef="0" cType="1" depth="3" nType="0" pos="r" purity="0.0e+00" res="0.0e+00" rms="0.0e+00">
          <Node Cut="5.5" IVar="5" NCoef="0" cType="1" depth="4" nType="0" pos="l" purity="0.0e+00" res="0.0e+00" rms="0.0e+00">
            <Node Cut="0.0e+00" IVar="-1" NCoef="0" cType="1" depth="5" nType="-99" pos="l" purity="0.0e+00" res="-0.0110756" rms="0.0e+00" />
            <Node Cut="0.0e+00" IVar="-1" NCoef="0" cType="1" depth="5" nType="-99" pos="r" purity="0.0e+00" res="0.00533281" rms="0.0e+00" />
          </Node>
          <Node Cut="0.0e+00" IVar="-1" NCoef="0" cType="1" depth="4" nType="-99" pos="r" purity="0.0e+00" res="0.0250634" rms="0.0e+00" />
        </Node>
      </Node>
      <Node Cut="0.0e+00" IVar="-1" NCoef="0" cType="1" depth="2" nType="-99" pos="r" purity="0.0e+00" res="-0.0326496" rms="0.0e+00" />
    </Node>
  </Node>
</BinaryTree>
