<BinaryTree boostWeight="1.0e+00" itree="374" type="DecisionTree">
  <Variables NVar="9" />
  <Node Cut="80.5" IVar="6" NCoef="0" cType="1" depth="0" nType="0" pos="s" purity="0.0e+00" res="0.0e+00" rms="0.0e+00">
    <Node Cut="79.5" IVar="6" NCoef="0" cType="1" depth="1" nType="0" pos="l" purity="0.0e+00" res="0.0e+00" rms="0.0e+00">
      <Node Cut="0.5" IVar="1" NCoef="0" cType="1" depth="2" nType="0" pos="l" purity="0.0e+00" res="0.0e+00" rms="0.0e+00">
        <Node Cut="71.5" IVar="6" NCoef="0" cType="1" depth="3" nType="0" pos="l" purity="0.0e+00" res="0.0e+00" rms="0.0e+00">
          <Node Cut="63.5" IVar="6" NCoef="0" cType="1" depth="4" nType="0" pos="l" purity="0.0e+00" res="0.0e+00" rms="0.0e+00">
            <Node Cut="0.0e+00" IVar="-1" NCoef="0" cType="1" depth="5" nType="-99" pos="l" purity="0.0e+00" res="0.000361001" rms="0.0e+00" />
            <Node Cut="0.0e+00" IVar="-1" NCoef="0" cType="1" depth="5" nType="-99" pos="r" purity="0.0e+00" res="-0.006436" rms="0.0e+00" />
          </Node>
          <Node Cut="4.5" IVar="5" NCoef="0" cType="1" depth="4" nType="0" pos="r" purity="0.0e+00" res="0.0e+00" rms="0.0e+00">
            <Node Cut="0.0e+00" IVar="-1" NCoef="0" cType="1" depth="5" nType="-99" pos="l" purity="0.0e+00" res="0.0023481" rms="0.0e+00" />
            <Node Cut="0.0e+00" IVar="-1" NCoef="0" cType="1" depth="5" nType="-99" pos="r" purity="0.0e+00" res="0.0366502" rms="0.0e+00" />
          </Node>
        </Node>
        <Node Cut="2.5" IVar="8" NCoef="0" cType="1" depth="3" nType="0" pos="r" purity="0.0e+00" res="0.0e+00" rms="0.0e+00">
          <Node Cut="4.5" IVar="6" NCoef="0" cType="1" depth="4" nType="0" pos="l" purity="0.0e+00" res="0.0e+00" rms="0.0e+00">
            <Node Cut="0.0e+00" IVar="-1" NCoef="0" cType="1" depth="5" nType="-99" pos="l" purity="0.0e+00" res="-0.0060088" rms="0.0e+00" />
            <Node Cut="0.0e+00" IVar="-1" NCoef="0" cType="1" depth="5" nType="-99" pos="r" purity="0.0e+00" res="0.0036849" rms="0.0e+00" />
          </Node>
          <Node Cut="70.5" IVar="6" NCoef="0" cType="1" depth="4" nType="0" pos="r" purity="0.0e+00" res="0.0e+00" rms="0.0e+00">
            <Node Cut="0.0e+00" IVar="-1" NCoef="0" cType="1" depth="5" nType="-99" pos="l" purity="0.0e+00" res="-0.000876138" rms="0.0e+00" />
            <Node Cut="0.0e+00" IVar="-1" NCoef="0" cType="1" depth="5" nType="-99" pos="r" purity="0.0e+00" res="-0.0149505" rms="0.0e+00" />
          </Node>
        </Node>
      </Node>
      <Node Cut="5" IVar="8" NCoef="0" cType="1" depth="2" nType="0" pos="r" purity="0.0e+00" res="0.0e+00" rms="0.0e+00">
        <Node Cut="3.5" IVar="4" NCoef="0" cType="1" depth="3" nType="0" pos="l" purity="0.0e+00" res="0.0e+00" rms="0.0e+00">
          <Node Cut="3" IVar="7" NCoef="0" cType="1" depth="4" nType="0" pos="l" purity="0.0e+00" res="0.0e+00" rms="0.0e+00">
            <Node Cut="0.0e+00" IVar="-1" NCoef="0" cType="1" depth="5" nType="-99" pos="l" purity="0.0e+00" res="-0.00369615" rms="0.0e+00" />
            <Node Cut="0.0e+00" IVar="-1" NCoef="0" cType="1" depth="5" nType="-99" pos="r" purity="0.0e+00" res="0.0172608" rms="0.0e+00" />
          </Node>
          <Node Cut="3" IVar="7" NCoef="0" cType="1" depth="4" nType="0" pos="r" purity="0.0e+00" res="0.0e+00" rms="0.0e+00">
            <Node Cut="0.0e+00" IVar="-1" NCoef="0" cType="1" depth="5" nType="-99" pos="l" purity="0.0e+00" res="-0.000361205" rms="0.0e+00" />
            <Node Cut="0.0e+00" IVar="-1" NCoef="0" cType="1" depth="5" nType="-99" pos="r" purity="0.0e+00" res="-0.0215927" rms="0.0e+00" />
          </Node>
        </Node>
        <Node Cut="0.0e+00" IVar="-1" NCoef="0" cType="1" depth="3" nType="-99" pos="r" purity="0.0e+00" res="0.0353884" rms="0.0e+00" />
      </Node>
    </Node>
    <Node Cut="85" IVar="6" NCoef="0" cType="1" depth="1" nType="0" pos="r" purity="0.0e+00" res="0.0e+00" rms="0.0e+00">
      <Node Cut="3.5" IVar="5" NCoef="0" cType="1" depth="2" nType="0" pos="l" purity="0.0e+00" res="0.0e+00" rms="0.0e+00">
        <Node Cut="0.0e+00" IVar="-1" NCoef="0" cType="1" depth="3" nType="-99" pos="l" purity="0.0e+00" res="0.0591613" rms="0.0e+00" />
        <Node Cut="4.5" IVar="8" NCoef="0" cType="1" depth="3" nType="0" pos="r" purity="0.0e+00" res="0.0e+00" rms="0.0e+00">
          <Node Cut="0.5" IVar="1" NCoef="0" cType="1" depth="4" nType="0" pos="l" purity="0.0e+00" res="0.0e+00" rms="0.0e+00">
            <Node Cut="0.0e+00" IVar="-1" NCoef="0" cType="1" depth="5" nType="-99" pos="l" purity="0.0e+00" res="-0.0226617" rms="0.0e+00" />
            <Node Cut="0.0e+00" IVar="-1" NCoef="0" cType="1" depth="5" nType="-99" pos="r" purity="0.0e+00" res="0.0123912" rms="0.0e+00" />
          </Node>
          <Node Cut="0.0e+00" IVar="-1" NCoef="0" cType="1" depth="4" nType="-99" pos="r" purity="0.0e+00" res="0.0315106" rms="0.0e+00" />
        </Node>
      </Node>
      <Node Cut="86.5" IVar="6" NCoef="0" cType="1" depth="2" nType="0" pos="r" purity="0.0e+00" res="0.0e+00" rms="0.0e+00">
        <Node Cut="2.5" IVar="8" NCoef="0" cType="1" depth="3" nType="0" pos="l" purity="0.0e+00" res="0.0e+00" rms="0.0e+00">
          <Node Cut="2.5" IVar="7" NCoef="0" cType="1" depth="4" nType="0" pos="l" purity="0.0e+00" res="0.0e+00" rms="0.0e+00">
            <Node Cut="0.0e+00" IVar="-1" NCoef="0" cType="1" depth="5" nType="-99" pos="l" purity="0.0e+00" res="0.01103" rms="0.0e+00" />
            <Node Cut="0.0e+00" IVar="-1" NCoef="0" cType="1" depth="5" nType="-99" pos="r" purity="0.0e+00" res="0.0343706" rms="0.0e+00" />
          </Node>
          <Node Cut="3" IVar="7" NCoef="0" cType="1" depth="4" nType="0" pos="r" purity="0.0e+00" res="0.0e+00" rms="0.0e+00">
            <Node Cut="0.0e+00" IVar="-1" NCoef="0" cType="1" depth="5" nType="-99" pos="l" purity="0.0e+00" res="-0.00529758" rms="0.0e+00" />
            <Node Cut="0.0e+00" IVar="-1" NCoef="0" cType="1" depth="5" nType="-99" pos="r" purity="0.0e+00" res="-0.0223828" rms="0.0e+00" />
          </Node>
        </Node>
        <Node Cut="10.5" IVar="8" NCoef="0" cType="1" depth="3" nType="0" pos="r" purity="0.0e+00" res="0.0e+00" rms="0.0e+00">
          <Node Cut="2.5" IVar="8" NCoef="0" cType="1" depth="4" nType="0" pos="l" purity="0.0e+00" res="0.0e+00" rms="0.0e+00">
            <Node Cut="0.0e+00" IVar="-1" NCoef="0" cType="1" depth="5" nType="-99" pos="l" purity="0.0e+00" res="-0.000805922" rms="0.0e+00" />
            <Node Cut="0.0e+00" IVar="-1" NCoef="0" cType="1" depth="5" nType="-99" pos="r" purity="0.0e+00" res="0.00114672" rms="0.0e+00" />
          </Node>
          <Node Cut="5.5" IVar="5" NCoef="0" cType="1" depth="4" nType="0" pos="r" purity="0.0e+00" res="0.0e+00" rms="0.0e+00">
            <Node Cut="0.0e+00" IVar="-1" NCoef="0" cType="1" depth="5" nType="-99" pos="l" purity="0.0e+00" res="-0.00121304" rms="0.0e+00" />
            <Node Cut="0.0e+00" IVar="-1" NCoef="0" cType="1" depth="5" nType="-99" pos="r" purity="0.0e+00" res="-0.00988293" rms="0.0e+00" />
          </Node>
        </Node>
      </Node>
    </Node>
  </Node>
</BinaryTree>
