<BinaryTree boostWeight="1.0e+00" itree="172" type="DecisionTree">
  <Variables NVar="12" />
  <Node Cut="4.5" IVar="11" NCoef="0" cType="1" depth="0" nType="0" pos="s" purity="0.0e+00" res="0.0e+00" rms="0.0e+00">
    <Node Cut="55.5" IVar="6" NCoef="0" cType="1" depth="1" nType="0" pos="l" purity="0.0e+00" res="0.0e+00" rms="0.0e+00">
      <Node Cut="1.5" IVar="9" NCoef="0" cType="1" depth="2" nType="0" pos="l" purity="0.0e+00" res="0.0e+00" rms="0.0e+00">
        <Node Cut="-79.5" IVar="8" NCoef="0" cType="1" depth="3" nType="0" pos="l" purity="0.0e+00" res="0.0e+00" rms="0.0e+00">
          <Node Cut="1.5" IVar="11" NCoef="0" cType="1" depth="4" nType="0" pos="l" purity="0.0e+00" res="0.0e+00" rms="0.0e+00">
            <Node Cut="0.0e+00" IVar="-1" NCoef="0" cType="1" depth="5" nType="-99" pos="l" purity="0.0e+00" res="-0.031853" rms="0.0e+00" />
            <Node Cut="0.0e+00" IVar="-1" NCoef="0" cType="1" depth="5" nType="-99" pos="r" purity="0.0e+00" res="0.0111215" rms="0.0e+00" />
          </Node>
          <Node Cut="138.5" IVar="7" NCoef="0" cType="1" depth="4" nType="0" pos="r" purity="0.0e+00" res="0.0e+00" rms="0.0e+00">
            <Node Cut="0.0e+00" IVar="-1" NCoef="0" cType="1" depth="5" nType="-99" pos="l" purity="0.0e+00" res="-0.079937" rms="0.0e+00" />
            <Node Cut="0.0e+00" IVar="-1" NCoef="0" cType="1" depth="5" nType="-99" pos="r" purity="0.0e+00" res="-0.0132375" rms="0.0e+00" />
          </Node>
        </Node>
        <Node Cut="54.5" IVar="6" NCoef="0" cType="1" depth="3" nType="0" pos="r" purity="0.0e+00" res="0.0e+00" rms="0.0e+00">
          <Node Cut="2.5" IVar="5" NCoef="0" cType="1" depth="4" nType="0" pos="l" purity="0.0e+00" res="0.0e+00" rms="0.0e+00">
            <Node Cut="0.0e+00" IVar="-1" NCoef="0" cType="1" depth="5" nType="-99" pos="l" purity="0.0e+00" res="-0.000298014" rms="0.0e+00" />
            <Node Cut="0.0e+00" IVar="-1" NCoef="0" cType="1" depth="5" nType="-99" pos="r" purity="0.0e+00" res="0.0561821" rms="0.0e+00" />
          </Node>
          <Node Cut="51" IVar="7" NCoef="0" cType="1" depth="4" nType="0" pos="r" purity="0.0e+00" res="0.0e+00" rms="0.0e+00">
            <Node Cut="0.0e+00" IVar="-1" NCoef="0" cType="1" depth="5" nType="-99" pos="l" purity="0.0e+00" res="-0.102217" rms="0.0e+00" />
            <Node Cut="0.0e+00" IVar="-1" NCoef="0" cType="1" depth="5" nType="-99" pos="r" purity="0.0e+00" res="0.0035086" rms="0.0e+00" />
          </Node>
        </Node>
      </Node>
      <Node Cut="-3.5" IVar="7" NCoef="0" cType="1" depth="2" nType="0" pos="r" purity="0.0e+00" res="0.0e+00" rms="0.0e+00">
        <Node Cut="-113.5" IVar="8" NCoef="0" cType="1" depth="3" nType="0" pos="l" purity="0.0e+00" res="0.0e+00" rms="0.0e+00">
          <Node Cut="2.5" IVar="9" NCoef="0" cType="1" depth="4" nType="0" pos="l" purity="0.0e+00" res="0.0e+00" rms="0.0e+00">
            <Node Cut="0.0e+00" IVar="-1" NCoef="0" cType="1" depth="5" nType="-99" pos="l" purity="0.0e+00" res="0.0214025" rms="0.0e+00" />
            <Node Cut="0.0e+00" IVar="-1" NCoef="0" cType="1" depth="5" nType="-99" pos="r" purity="0.0e+00" res="-0.00500941" rms="0.0e+00" />
          </Node>
          <Node Cut="2.5" IVar="9" NCoef="0" cType="1" depth="4" nType="0" pos="r" purity="0.0e+00" res="0.0e+00" rms="0.0e+00">
            <Node Cut="0.0e+00" IVar="-1" NCoef="0" cType="1" depth="5" nType="-99" pos="l" purity="0.0e+00" res="-0.00906448" rms="0.0e+00" />
            <Node Cut="0.0e+00" IVar="-1" NCoef="0" cType="1" depth="5" nType="-99" pos="r" purity="0.0e+00" res="0.110685" rms="0.0e+00" />
          </Node>
        </Node>
        <Node Cut="5.5" IVar="7" NCoef="0" cType="1" depth="3" nType="0" pos="r" purity="0.0e+00" res="0.0e+00" rms="0.0e+00">
          <Node Cut="4.5" IVar="7" NCoef="0" cType="1" depth="4" nType="0" pos="l" purity="0.0e+00" res="0.0e+00" rms="0.0e+00">
            <Node Cut="0.0e+00" IVar="-1" NCoef="0" cType="1" depth="5" nType="-99" pos="l" purity="0.0e+00" res="-0.00157048" rms="0.0e+00" />
            <Node Cut="0.0e+00" IVar="-1" NCoef="0" cType="1" depth="5" nType="-99" pos="r" purity="0.0e+00" res="-0.0979633" rms="0.0e+00" />
          </Node>
          <Node Cut="10.5" IVar="7" NCoef="0" cType="1" depth="4" nType="0" pos="r" purity="0.0e+00" res="0.0e+00" rms="0.0e+00">
            <Node Cut="0.0e+00" IVar="-1" NCoef="0" cType="1" depth="5" nType="-99" pos="l" purity="0.0e+00" res="0.0471497" rms="0.0e+00" />
            <Node Cut="0.0e+00" IVar="-1" NCoef="0" cType="1" depth="5" nType="-99" pos="r" purity="0.0e+00" res="0.000453864" rms="0.0e+00" />
          </Node>
        </Node>
      </Node>
    </Node>
    <Node Cut="154.5" IVar="6" NCoef="0" cType="1" depth="1" nType="0" pos="r" purity="0.0e+00" res="0.0e+00" rms="0.0e+00">
      <Node Cut="129" IVar="6" NCoef="0" cType="1" depth="2" nType="0" pos="l" purity="0.0e+00" res="0.0e+00" rms="0.0e+00">
        <Node Cut="6.5" IVar="11" NCoef="0" cType="1" depth="3" nType="0" pos="l" purity="0.0e+00" res="0.0e+00" rms="0.0e+00">
          <Node Cut="5.5" IVar="9" NCoef="0" cType="1" depth="4" nType="0" pos="l" purity="0.0e+00" res="0.0e+00" rms="0.0e+00">
            <Node Cut="0.0e+00" IVar="-1" NCoef="0" cType="1" depth="5" nType="-99" pos="l" purity="0.0e+00" res="-0.00300245" rms="0.0e+00" />
            <Node Cut="0.0e+00" IVar="-1" NCoef="0" cType="1" depth="5" nType="-99" pos="r" purity="0.0e+00" res="0.0280192" rms="0.0e+00" />
          </Node>
          <Node Cut="1.5" IVar="9" NCoef="0" cType="1" depth="4" nType="0" pos="r" purity="0.0e+00" res="0.0e+00" rms="0.0e+00">
            <Node Cut="0.0e+00" IVar="-1" NCoef="0" cType="1" depth="5" nType="-99" pos="l" purity="0.0e+00" res="0.00206884" rms="0.0e+00" />
            <Node Cut="0.0e+00" IVar="-1" NCoef="0" cType="1" depth="5" nType="-99" pos="r" purity="0.0e+00" res="-3.46525e-05" rms="0.0e+00" />
          </Node>
        </Node>
        <Node Cut="0.5" IVar="10" NCoef="0" cType="1" depth="3" nType="0" pos="r" purity="0.0e+00" res="0.0e+00" rms="0.0e+00">
          <Node Cut="1.5" IVar="5" NCoef="0" cType="1" depth="4" nType="0" pos="l" purity="0.0e+00" res="0.0e+00" rms="0.0e+00">
            <Node Cut="0.0e+00" IVar="-1" NCoef="0" cType="1" depth="5" nType="-99" pos="l" purity="0.0e+00" res="0.000518541" rms="0.0e+00" />
            <Node Cut="0.0e+00" IVar="-1" NCoef="0" cType="1" depth="5" nType="-99" pos="r" purity="0.0e+00" res="0.00657011" rms="0.0e+00" />
          </Node>
          <Node Cut="2.5" IVar="9" NCoef="0" cType="1" depth="4" nType="0" pos="r" purity="0.0e+00" res="0.0e+00" rms="0.0e+00">
            <Node Cut="0.0e+00" IVar="-1" NCoef="0" cType="1" depth="5" nType="-99" pos="l" purity="0.0e+00" res="-0.00154457" rms="0.0e+00" />
            <Node Cut="0.0e+00" IVar="-1" NCoef="0" cType="1" depth="5" nType="-99" pos="r" purity="0.0e+00" res="-0.0169477" rms="0.0e+00" />
          </Node>
        </Node>
      </Node>
      <Node Cut="29" IVar="7" NCoef="0" cType="1" depth="2" nType="0" pos="r" purity="0.0e+00" res="0.0e+00" rms="0.0e+00">
        <Node Cut="0.5" IVar="0" NCoef="0" cType="1" depth="3" nType="0" pos="l" purity="0.0e+00" res="0.0e+00" rms="0.0e+00">
          <Node Cut="2.5" IVar="5" NCoef="0" cType="1" depth="4" nType="0" pos="l" purity="0.0e+00" res="0.0e+00" rms="0.0e+00">
            <Node Cut="0.0e+00" IVar="-1" NCoef="0" cType="1" depth="5" nType="-99" pos="l" purity="0.0e+00" res="-0.0681259" rms="0.0e+00" />
            <Node Cut="0.0e+00" IVar="-1" NCoef="0" cType="1" depth="5" nType="-99" pos="r" purity="0.0e+00" res="0.0150223" rms="0.0e+00" />
          </Node>
          <Node Cut="3.5" IVar="9" NCoef="0" cType="1" depth="4" nType="0" pos="r" purity="0.0e+00" res="0.0e+00" rms="0.0e+00">
            <Node Cut="0.0e+00" IVar="-1" NCoef="0" cType="1" depth="5" nType="-99" pos="l" purity="0.0e+00" res="-0.00856683" rms="0.0e+00" />
            <Node Cut="0.0e+00" IVar="-1" NCoef="0" cType="1" depth="5" nType="-99" pos="r" purity="0.0e+00" res="0.0363008" rms="0.0e+00" />
          </Node>
        </Node>
        <Node Cut="88.5" IVar="7" NCoef="0" cType="1" depth="3" nType="0" pos="r" purity="0.0e+00" res="0.0e+00" rms="0.0e+00">
          <Node Cut="2.5" IVar="9" NCoef="0" cType="1" depth="4" nType="0" pos="l" purity="0.0e+00" res="0.0e+00" rms="0.0e+00">
            <Node Cut="0.0e+00" IVar="-1" NCoef="0" cType="1" depth="5" nType="-99" pos="l" purity="0.0e+00" res="-0.00619683" rms="0.0e+00" />
            <Node Cut="0.0e+00" IVar="-1" NCoef="0" cType="1" depth="5" nType="-99" pos="r" purity="0.0e+00" res="0.0274367" rms="0.0e+00" />
          </Node>
          <Node Cut="1.5" IVar="5" NCoef="0" cType="1" depth="4" nType="0" pos="r" purity="0.0e+00" res="0.0e+00" rms="0.0e+00">
            <Node Cut="0.0e+00" IVar="-1" NCoef="0" cType="1" depth="5" nType="-99" pos="l" purity="0.0e+00" res="-0.00625289" rms="0.0e+00" />
            <Node Cut="0.0e+00" IVar="-1" NCoef="0" cType="1" depth="5" nType="-99" pos="r" purity="0.0e+00" res="-0.000464871" rms="0.0e+00" />
          </Node>
        </Node>
      </Node>
    </Node>
  </Node>
</BinaryTree>
