<BinaryTree boostWeight="1.0e+00" itree="74" type="DecisionTree">
  <Variables NVar="12" />
  <Node Cut="25.5" IVar="11" NCoef="0" cType="1" depth="0" nType="0" pos="s" purity="0.0e+00" res="0.0e+00" rms="0.0e+00">
    <Node Cut="5.5" IVar="11" NCoef="0" cType="1" depth="1" nType="0" pos="l" purity="0.0e+00" res="0.0e+00" rms="0.0e+00">
      <Node Cut="11.5" IVar="8" NCoef="0" cType="1" depth="2" nType="0" pos="l" purity="0.0e+00" res="0.0e+00" rms="0.0e+00">
        <Node Cut="-32.5" IVar="8" NCoef="0" cType="1" depth="3" nType="0" pos="l" purity="0.0e+00" res="0.0e+00" rms="0.0e+00">
          <Node Cut="1.5" IVar="5" NCoef="0" cType="1" depth="4" nType="0" pos="l" purity="0.0e+00" res="0.0e+00" rms="0.0e+00">
            <Node Cut="0.0e+00" IVar="-1" NCoef="0" cType="1" depth="5" nType="-99" pos="l" purity="0.0e+00" res="0.0149822" rms="0.0e+00" />
            <Node Cut="0.0e+00" IVar="-1" NCoef="0" cType="1" depth="5" nType="-99" pos="r" purity="0.0e+00" res="-0.00173152" rms="0.0e+00" />
          </Node>
          <Node Cut="6.5" IVar="9" NCoef="0" cType="1" depth="4" nType="0" pos="r" purity="0.0e+00" res="0.0e+00" rms="0.0e+00">
            <Node Cut="0.0e+00" IVar="-1" NCoef="0" cType="1" depth="5" nType="-99" pos="l" purity="0.0e+00" res="-0.00205846" rms="0.0e+00" />
            <Node Cut="0.0e+00" IVar="-1" NCoef="0" cType="1" depth="5" nType="-99" pos="r" purity="0.0e+00" res="0.0204381" rms="0.0e+00" />
          </Node>
        </Node>
        <Node Cut="50.5" IVar="7" NCoef="0" cType="1" depth="3" nType="0" pos="r" purity="0.0e+00" res="0.0e+00" rms="0.0e+00">
          <Node Cut="29.5" IVar="8" NCoef="0" cType="1" depth="4" nType="0" pos="l" purity="0.0e+00" res="0.0e+00" rms="0.0e+00">
            <Node Cut="0.0e+00" IVar="-1" NCoef="0" cType="1" depth="5" nType="-99" pos="l" purity="0.0e+00" res="-0.00435737" rms="0.0e+00" />
            <Node Cut="0.0e+00" IVar="-1" NCoef="0" cType="1" depth="5" nType="-99" pos="r" purity="0.0e+00" res="-0.0538049" rms="0.0e+00" />
          </Node>
          <Node Cut="13.5" IVar="6" NCoef="0" cType="1" depth="4" nType="0" pos="r" purity="0.0e+00" res="0.0e+00" rms="0.0e+00">
            <Node Cut="0.0e+00" IVar="-1" NCoef="0" cType="1" depth="5" nType="-99" pos="l" purity="0.0e+00" res="0.0470715" rms="0.0e+00" />
            <Node Cut="0.0e+00" IVar="-1" NCoef="0" cType="1" depth="5" nType="-99" pos="r" purity="0.0e+00" res="0.00197759" rms="0.0e+00" />
          </Node>
        </Node>
      </Node>
      <Node Cut="0.5" IVar="10" NCoef="0" cType="1" depth="2" nType="0" pos="r" purity="0.0e+00" res="0.0e+00" rms="0.0e+00">
        <Node Cut="61.5" IVar="8" NCoef="0" cType="1" depth="3" nType="0" pos="l" purity="0.0e+00" res="0.0e+00" rms="0.0e+00">
          <Node Cut="0.5" IVar="5" NCoef="0" cType="1" depth="4" nType="0" pos="l" purity="0.0e+00" res="0.0e+00" rms="0.0e+00">
            <Node Cut="0.0e+00" IVar="-1" NCoef="0" cType="1" depth="5" nType="-99" pos="l" purity="0.0e+00" res="0.0237897" rms="0.0e+00" />
            <Node Cut="0.0e+00" IVar="-1" NCoef="0" cType="1" depth="5" nType="-99" pos="r" purity="0.0e+00" res="0.00151663" rms="0.0e+00" />
          </Node>
          <Node Cut="0.5" IVar="3" NCoef="0" cType="1" depth="4" nType="0" pos="r" purity="0.0e+00" res="0.0e+00" rms="0.0e+00">
            <Node Cut="0.0e+00" IVar="-1" NCoef="0" cType="1" depth="5" nType="-99" pos="l" purity="0.0e+00" res="0.0134568" rms="0.0e+00" />
            <Node Cut="0.0e+00" IVar="-1" NCoef="0" cType="1" depth="5" nType="-99" pos="r" purity="0.0e+00" res="-0.0444977" rms="0.0e+00" />
          </Node>
        </Node>
        <Node Cut="63.5" IVar="7" NCoef="0" cType="1" depth="3" nType="0" pos="r" purity="0.0e+00" res="0.0e+00" rms="0.0e+00">
          <Node Cut="-3.5" IVar="8" NCoef="0" cType="1" depth="4" nType="0" pos="l" purity="0.0e+00" res="0.0e+00" rms="0.0e+00">
            <Node Cut="0.0e+00" IVar="-1" NCoef="0" cType="1" depth="5" nType="-99" pos="l" purity="0.0e+00" res="-0.00174509" rms="0.0e+00" />
            <Node Cut="0.0e+00" IVar="-1" NCoef="0" cType="1" depth="5" nType="-99" pos="r" purity="0.0e+00" res="0.00160653" rms="0.0e+00" />
          </Node>
          <Node Cut="6.5" IVar="9" NCoef="0" cType="1" depth="4" nType="0" pos="r" purity="0.0e+00" res="0.0e+00" rms="0.0e+00">
            <Node Cut="0.0e+00" IVar="-1" NCoef="0" cType="1" depth="5" nType="-99" pos="l" purity="0.0e+00" res="-0.0020352" rms="0.0e+00" />
            <Node Cut="0.0e+00" IVar="-1" NCoef="0" cType="1" depth="5" nType="-99" pos="r" purity="0.0e+00" res="-0.0216356" rms="0.0e+00" />
          </Node>
        </Node>
      </Node>
    </Node>
    <Node Cut="36.5" IVar="6" NCoef="0" cType="1" depth="1" nType="0" pos="r" purity="0.0e+00" res="0.0e+00" rms="0.0e+00">
      <Node Cut="-0.5" IVar="8" NCoef="0" cType="1" depth="2" nType="0" pos="l" purity="0.0e+00" res="0.0e+00" rms="0.0e+00">
        <Node Cut="-4.5" IVar="8" NCoef="0" cType="1" depth="3" nType="0" pos="l" purity="0.0e+00" res="0.0e+00" rms="0.0e+00">
          <Node Cut="-22" IVar="8" NCoef="0" cType="1" depth="4" nType="0" pos="l" purity="0.0e+00" res="0.0e+00" rms="0.0e+00">
            <Node Cut="0.0e+00" IVar="-1" NCoef="0" cType="1" depth="5" nType="-99" pos="l" purity="0.0e+00" res="-0.0155872" rms="0.0e+00" />
            <Node Cut="0.0e+00" IVar="-1" NCoef="0" cType="1" depth="5" nType="-99" pos="r" purity="0.0e+00" res="-0.0524221" rms="0.0e+00" />
          </Node>
          <Node Cut="-0.5" IVar="7" NCoef="0" cType="1" depth="4" nType="0" pos="r" purity="0.0e+00" res="0.0e+00" rms="0.0e+00">
            <Node Cut="0.0e+00" IVar="-1" NCoef="0" cType="1" depth="5" nType="-99" pos="l" purity="0.0e+00" res="0.014052" rms="0.0e+00" />
            <Node Cut="0.0e+00" IVar="-1" NCoef="0" cType="1" depth="5" nType="-99" pos="r" purity="0.0e+00" res="-0.02559" rms="0.0e+00" />
          </Node>
        </Node>
        <Node Cut="0.5" IVar="5" NCoef="0" cType="1" depth="3" nType="0" pos="r" purity="0.0e+00" res="0.0e+00" rms="0.0e+00">
          <Node Cut="0.0e+00" IVar="-1" NCoef="0" cType="1" depth="4" nType="-99" pos="l" purity="0.0e+00" res="0.0349852" rms="0.0e+00" />
          <Node Cut="9.5" IVar="8" NCoef="0" cType="1" depth="4" nType="0" pos="r" purity="0.0e+00" res="0.0e+00" rms="0.0e+00">
            <Node Cut="0.0e+00" IVar="-1" NCoef="0" cType="1" depth="5" nType="-99" pos="l" purity="0.0e+00" res="0.00226604" rms="0.0e+00" />
            <Node Cut="0.0e+00" IVar="-1" NCoef="0" cType="1" depth="5" nType="-99" pos="r" purity="0.0e+00" res="-0.0307549" rms="0.0e+00" />
          </Node>
        </Node>
      </Node>
      <Node Cut="1.5" IVar="5" NCoef="0" cType="1" depth="2" nType="0" pos="r" purity="0.0e+00" res="0.0e+00" rms="0.0e+00">
        <Node Cut="0.0e+00" IVar="-1" NCoef="0" cType="1" depth="3" nType="-99" pos="l" purity="0.0e+00" res="0.0482714" rms="0.0e+00" />
        <Node Cut="-9.5" IVar="8" NCoef="0" cType="1" depth="3" nType="0" pos="r" purity="0.0e+00" res="0.0e+00" rms="0.0e+00">
          <Node Cut="32.5" IVar="7" NCoef="0" cType="1" depth="4" nType="0" pos="l" purity="0.0e+00" res="0.0e+00" rms="0.0e+00">
            <Node Cut="0.0e+00" IVar="-1" NCoef="0" cType="1" depth="5" nType="-99" pos="l" purity="0.0e+00" res="0.00205583" rms="0.0e+00" />
            <Node Cut="0.0e+00" IVar="-1" NCoef="0" cType="1" depth="5" nType="-99" pos="r" purity="0.0e+00" res="0.036348" rms="0.0e+00" />
          </Node>
          <Node Cut="53" IVar="6" NCoef="0" cType="1" depth="4" nType="0" pos="r" purity="0.0e+00" res="0.0e+00" rms="0.0e+00">
            <Node Cut="0.0e+00" IVar="-1" NCoef="0" cType="1" depth="5" nType="-99" pos="l" purity="0.0e+00" res="-7.32108e-05" rms="0.0e+00" />
            <Node Cut="0.0e+00" IVar="-1" NCoef="0" cType="1" depth="5" nType="-99" pos="r" purity="0.0e+00" res="-0.0168718" rms="0.0e+00" />
          </Node>
        </Node>
      </Node>
    </Node>
  </Node>
</BinaryTree>
